examples/phase1_milestone/sync_fifo.v
// sync_fifo.v
//
// Phase 1 milestone: synchronous FIFO design + directed, self-checking
// testbench (see notes/2026-08-23-phase1-milestone-sync-fifo.md).
//
// Single-clock-domain synchronous FIFO, parameterized in data width and
// depth (depth = 2**ADDR_WIDTH). Deliberately single-clock: cross-clock-
// domain (CDC) FIFO design with gray-coded pointers and synchronizers is
// Phase 6 material ("CDC verification basics" in the roadmap README);
// this milestone is scoped to the single-clock case to match where
// Phase 1 sits in the roadmap.
//
// Design technique: full/empty disambiguation via one extra pointer bit.
// wr_ptr and rd_ptr are each (ADDR_WIDTH+1) bits wide. The bottom
// ADDR_WIDTH bits index into the memory array; the extra top bit acts as
// a wrap-count parity bit. This is the standard technique for
// distinguishing "completely full" from "completely empty" without a
// separate counter, and generalizes directly to the gray-coded version
// used in async/CDC FIFOs (a natural Phase 6 extension of this exact
// module):
//   empty  <=> wr_ptr == rd_ptr                       (all bits equal)
//   full   <=> same lower ADDR_WIDTH bits, but the top
//              (wrap) bit differs (wr_ptr has wrapped
//              one more time than rd_ptr)
//
// Read is combinational (data_out reflects mem[rd_ptr] immediately,
// "first-word-fall-through" style) rather than registered, which keeps
// the read-side timing simple for this milestone; a registered-read
// variant (one cycle of read latency, common in higher-throughput
// designs) is a natural follow-up noted in the milestone summary.

`timescale 1ns/1ps

module sync_fifo #(
    parameter WIDTH      = 8,
    parameter ADDR_WIDTH = 3   // depth = 2**ADDR_WIDTH = 8 entries
) (
    input  logic                  clk,
    input  logic                  rst_n,     // synchronous, active-low

    input  logic                  wr_en,
    input  logic [WIDTH-1:0]      wr_data,
    output logic                  full,

    input  logic                  rd_en,
    output logic [WIDTH-1:0]      rd_data,
    output logic                  empty
);

    localparam DEPTH = (1 << ADDR_WIDTH);

    logic [WIDTH-1:0]      mem [0:DEPTH-1];
    logic [ADDR_WIDTH:0]   wr_ptr, rd_ptr;   // extra MSB = wrap bit

    // ---------------------------------------------------------------
    // Status flags (combinational -- pure function of the two pointers)
    // ---------------------------------------------------------------
    assign empty = (wr_ptr == rd_ptr);
    assign full  = (wr_ptr[ADDR_WIDTH-1:0] == rd_ptr[ADDR_WIDTH-1:0]) &&
                   (wr_ptr[ADDR_WIDTH]     != rd_ptr[ADDR_WIDTH]);

    // First-word-fall-through combinational read data.
    assign rd_data = mem[rd_ptr[ADDR_WIDTH-1:0]];

    // ---------------------------------------------------------------
    // Write side. wr_en while full is a protocol violation (dropped,
    // not corrupting the FIFO) -- flagged via an explicit runtime check
    // ($error) rather than silently ignored, so a testbench driving an
    // illegal write-while-full sequence gets a loud signal rather than a
    // quietly-swallowed bug. (SystemVerilog immediate `assert (...) else
    // $error(...)` would be the more idiomatic way to write this check,
    // but Icarus Verilog 10.3 -- the simulator available in this
    // sandbox, see tools/setup_iverilog.sh -- does not implement
    // immediate assertion statements ["sorry: Simple immediate assertion
    // statements not implemented"], so a plain `if` is used instead; the
    // semantic intent is identical, and this is worth revisiting with
    // `assert` syntax on a simulator with full SVA support.) This
    // mirrors how a real verification environment would treat a DUT-
    // external protocol violation: it is the *testbench's* job not to do
    // this, and the check exists to catch a testbench bug, not to
    // specify DUT recovery behavior.
    // ---------------------------------------------------------------
    always @(posedge clk) begin
        if (!rst_n) begin
            wr_ptr <= '0;
        end else begin
            if (wr_en) begin
                // synthesis translate_off
                if (full)
                    $error("sync_fifo: wr_en asserted while full=1 at time %0t -- write dropped, pointer not advanced (protocol violation, not a design feature)", $time);
                // synthesis translate_on
                if (!full) begin
                    mem[wr_ptr[ADDR_WIDTH-1:0]] <= wr_data;
                    wr_ptr <= wr_ptr + 1'b1;
                end
            end
        end
    end

    // ---------------------------------------------------------------
    // Read side. Symmetric treatment: rd_en while empty is a protocol
    // violation, flagged the same way.
    // ---------------------------------------------------------------
    always @(posedge clk) begin
        if (!rst_n) begin
            rd_ptr <= '0;
        end else begin
            if (rd_en) begin
                // synthesis translate_off
                if (empty)
                    $error("sync_fifo: rd_en asserted while empty=1 at time %0t -- read ignored, pointer not advanced (protocol violation, not a design feature)", $time);
                // synthesis translate_on
                if (!empty) begin
                    rd_ptr <= rd_ptr + 1'b1;
                end
            end
        end
    end

endmodule

examples/phase1_milestone/sync_fifo_directed_tb.v
// sync_fifo_directed_tb.v
//
// Directed, self-checking testbench for sync_fifo.v (Phase 1 milestone).
// See notes/2026-08-23-phase1-milestone-sync-fifo.md for the test plan
// this file implements.
//
// Run with Icarus Verilog (see tools/setup_iverilog.sh if iverilog is
// not already installed):
//   iverilog -g2012 -o sim sync_fifo.v sync_fifo_directed_tb.v
//   vvp sim
//   gtkwave sync_fifo_wave.vcd   (waveform dump, for local GTKWave use --
//                                  GTKWave itself is not available in the
//                                  automation sandbox this was authored
//                                  in; the dump is generated and verified
//                                  non-empty as evidence the dump
//                                  mechanism works, per the roadmap
//                                  milestone description)
//
// Self-checking approach: an independent SystemVerilog queue (`logic
// [WIDTH-1:0] ref_model[$]`) tracks expected FIFO contents, driven by
// the exact same push/pop discipline the DUT is specified to implement --
// but implemented with a completely different underlying data structure
// (dynamic queue vs. the DUT's fixed-size circular-buffer-with-wrapping-
// pointers), so the reference model cannot share a pointer-arithmetic
// bug with the DUT.

`timescale 1ns/1ps

module tb_sync_fifo;

    localparam WIDTH      = 8;
    localparam ADDR_WIDTH = 3;
    localparam DEPTH      = (1 << ADDR_WIDTH);

    logic                 clk = 0;
    logic                 rst_n;
    logic                 wr_en;
    logic [WIDTH-1:0]     wr_data;
    logic                 full;
    logic                 rd_en;
    logic [WIDTH-1:0]     rd_data;
    logic                 empty;

    sync_fifo #(.WIDTH(WIDTH), .ADDR_WIDTH(ADDR_WIDTH)) dut (
        .clk(clk), .rst_n(rst_n),
        .wr_en(wr_en), .wr_data(wr_data), .full(full),
        .rd_en(rd_en), .rd_data(rd_data), .empty(empty)
    );

    always #5 clk = ~clk;   // 10 ns period

    // Independent software reference model (dynamic queue).
    logic [WIDTH-1:0] ref_model[$];

    integer errors = 0;
    integer checks = 0;
    logic [WIDTH-1:0] next_push_value = 8'h01;

    // ---------------------------------------------------------------
    // Directed-stimulus tasks. Each drives exactly one clock cycle of
    // wr_en/rd_en, updates the reference model ONLY when the operation
    // was legal (mirroring exactly what the DUT's pointers are specified
    // to do -- an illegal push/pop must leave both the DUT and the
    // reference model unchanged, or the two would silently desync), and
    // checks status flags (and, for reads, data) against the reference
    // model.
    // ---------------------------------------------------------------

    task automatic check_flags(input string tag);
        logic exp_empty, exp_full;
        begin
            exp_empty = (ref_model.size() == 0);
            exp_full  = (ref_model.size() == DEPTH);
            checks = checks + 1;
            if (empty !== exp_empty) begin
                errors = errors + 1;
                $display("[FAIL][%s] t=%0t: empty=%b, expected %b (ref size=%0d)",
                          tag, $time, empty, exp_empty, ref_model.size());
            end
            checks = checks + 1;
            if (full !== exp_full) begin
                errors = errors + 1;
                $display("[FAIL][%s] t=%0t: full=%b, expected %b (ref size=%0d)",
                          tag, $time, full, exp_full, ref_model.size());
            end
        end
    endtask

    task automatic do_push(input string tag);
        logic [WIDTH-1:0] pushed_value;
        logic              was_full;
        begin
            pushed_value = next_push_value;
            was_full = full;
            wr_data = pushed_value;
            wr_en   = 1'b1;
            rd_en   = 1'b0;
            @(posedge clk);
            #1; // let pointers/flags settle post-edge before sampling
            if (!was_full) begin
                ref_model.push_back(pushed_value);
                next_push_value = next_push_value + 1'b1;
            end
            wr_en = 1'b0;
            check_flags(tag);
        end
    endtask

    task automatic do_pop(input string tag);
        logic [WIDTH-1:0] exp_data;
        logic              was_empty;
        begin
            rd_en = 1'b1;
            wr_en = 1'b0;
            // Sample rd_data (combinational, first-word-fall-through)
            // BEFORE the clock edge that consumes it -- rd_data reflects
            // the CURRENT front-of-queue entry, not the entry after this
            // pop takes effect.
            #1;
            was_empty = empty;
            if (!was_empty) begin
                exp_data = ref_model[0];
                checks = checks + 1;
                if (rd_data !== exp_data) begin
                    errors = errors + 1;
                    $display("[FAIL][%s] t=%0t: rd_data=%0d, expected %0d",
                              tag, $time, rd_data, exp_data);
                end
            end
            @(posedge clk);
            #1;
            if (!was_empty) exp_data = ref_model.pop_front();
            rd_en = 1'b0;
            check_flags(tag);
        end
    endtask

    // Combined push+pop in the SAME cycle (tests that both pointers can
    // advance together without interfering with each other).
    task automatic do_push_and_pop(input string tag);
        logic [WIDTH-1:0] pushed_value;
        logic [WIDTH-1:0] exp_pop_data;
        logic              was_empty, was_full;
        begin
            pushed_value = next_push_value;
            wr_data = pushed_value;
            wr_en   = 1'b1;
            rd_en   = 1'b1;
            #1;
            was_empty = empty;
            was_full  = full;
            if (!was_empty) begin
                exp_pop_data = ref_model[0];
                checks = checks + 1;
                if (rd_data !== exp_pop_data) begin
                    errors = errors + 1;
                    $display("[FAIL][%s] t=%0t: rd_data=%0d, expected %0d",
                              tag, $time, rd_data, exp_pop_data);
                end
            end
            @(posedge clk);
            #1;
            if (!was_full)  begin
                ref_model.push_back(pushed_value);
                next_push_value = next_push_value + 1'b1;
            end
            if (!was_empty) exp_pop_data = ref_model.pop_front();
            wr_en = 1'b0;
            rd_en = 1'b0;
            check_flags(tag);
        end
    endtask

    initial begin
        $dumpfile("sync_fifo_wave.vcd");
        $dumpvars(0, tb_sync_fifo);

        wr_en = 0; rd_en = 0; wr_data = '0;
        rst_n = 0;
        repeat (2) @(posedge clk);
        #1;

        // --- Test 1: reset state ---
        check_flags("reset");

        rst_n = 1;
        @(posedge clk);
        #1;
        check_flags("post-reset-release");

        // --- Test 2: fill to full ---
        for (int i = 0; i < DEPTH; i++) do_push("fill-to-full");

        // --- Test 3: illegal push while full (protocol violation --
        // expect an $error from the DUT's assertion in the sim log;
        // reference model correctly does NOT record this push since
        // do_push only advances it when the pointer wasn't already full) ---
        do_push("illegal-push-while-full");

        // --- Test 4: drain to empty, checking FIFO ordering ---
        for (int i = 0; i < DEPTH; i++) do_pop("drain-to-empty");

        // --- Test 5: illegal pop while empty (protocol violation) ---
        do_pop("illegal-pop-while-empty");

        // --- Test 6: wrap-around stress -- push 5, pop 3, push 6 more
        // (crosses the 8-entry pointer wrap boundary), then drain fully,
        // checking ordering throughout ---
        for (int i = 0; i < 5; i++) do_push("wrap-fill-1");
        for (int i = 0; i < 3; i++) do_pop("wrap-drain-1");
        for (int i = 0; i < 6; i++) do_push("wrap-fill-2");
        while (ref_model.size() > 0) do_pop("wrap-drain-2");

        // --- Test 7: simultaneous push+pop across several cycles,
        // starting from empty (first push must land while empty, then
        // steady-state push+pop) ---
        do_push("simul-seed");
        for (int i = 0; i < 10; i++) do_push_and_pop("simul-push-pop");
        do_pop("simul-drain-last");

        $display("---------------------------------------------------------");
        $display("Total checks = %0d, errors = %0d", checks, errors);
        if (errors == 0)
            $display("PASS: sync_fifo matched the reference model on every checked cycle across all 7 directed test phases.");
        else
            $display("FAIL: sync_fifo had %0d mismatch(es) against the reference model.", errors);

        $finish;
    end

endmodule

examples/phase1_milestone/sync_fifo_wave.vcd
$date
	Sun Aug 23 23:22:49 2026
$end
$version
	Icarus Verilog
$end
$timescale
	1ps
$end
$scope module tb_sync_fifo $end
$var wire 8 ! rd_data [7:0] $end
$var wire 1 " full $end
$var wire 1 # empty $end
$var reg 1 $ clk $end
$var reg 8 % next_push_value [7:0] $end
$var reg 1 & rd_en $end
$var reg 1 ' rst_n $end
$var reg 8 ( wr_data [7:0] $end
$var reg 1 ) wr_en $end
$var integer 32 * checks [31:0] $end
$var integer 32 + errors [31:0] $end
$scope module dut $end
$var wire 1 $ clk $end
$var wire 1 " full $end
$var wire 8 , rd_data [7:0] $end
$var wire 1 & rd_en $end
$var wire 1 ' rst_n $end
$var wire 8 - wr_data [7:0] $end
$var wire 1 ) wr_en $end
$var wire 1 # empty $end
$var reg 4 . rd_ptr [3:0] $end
$var reg 4 / wr_ptr [3:0] $end
$upscope $end
$scope begin $ivl_for_loop0 $end
$var integer 32 0 i [31:0] $end
$upscope $end
$scope begin $ivl_for_loop1 $end
$var integer 32 1 i [31:0] $end
$upscope $end
$scope begin $ivl_for_loop2 $end
$var integer 32 2 i [31:0] $end
$upscope $end
$scope begin $ivl_for_loop3 $end
$var integer 32 3 i [31:0] $end
$upscope $end
$scope begin $ivl_for_loop4 $end
$var integer 32 4 i [31:0] $end
$upscope $end
$scope begin $ivl_for_loop5 $end
$var integer 32 5 i [31:0] $end
$upscope $end
$scope task check_flags $end
$upscope $end
$scope task do_pop $end
$upscope $end
$scope task do_push $end
$upscope $end
$scope task do_push_and_pop $end
$upscope $end
$upscope $end
$enddefinitions $end
#0
$dumpvars
b0 5
b0 4
b0 3
b0 2
b0 1
b0 0
bx /
bx .
b0 -
bx ,
b0 +
b0 *
0)
b0 (
0'
0&
b1 %
0$
x#
x"
bx !
$end
#5000
0"
1#
b0 /
b0 .
1$
#10000
0$
#15000
1$
#16000
1'
b10 *
#20000
0$
#25000
1$
#26000
1)
b1 (
b1 -
b100 *
#30000
0$
#35000
0#
b1 /
b1 !
b1 ,
1$
#36000
b10 (
b10 -
b1 0
b110 *
1)
b10 %
#40000
0$
#45000
b10 /
1$
#46000
b11 (
b11 -
b10 0
b1000 *
1)
b11 %
#50000
0$
#55000
b11 /
1$
#56000
b100 (
b100 -
b11 0
b1010 *
1)
b100 %
#60000
0$
#65000
b100 /
1$
#66000
b101 (
b101 -
b100 0
b1100 *
1)
b101 %
#70000
0$
#75000
b101 /
1$
#76000
b110 (
b110 -
b101 0
b1110 *
1)
b110 %
#80000
0$
#85000
b110 /
1$
#86000
b111 (
b111 -
b110 0
b10000 *
1)
b111 %
#90000
0$
#95000
b111 /
1$
#96000
b1000 (
b1000 -
b111 0
b10010 *
1)
b1000 %
#100000
0$
#105000
1"
b1000 /
1$
#106000
b1001 (
b1001 -
b1000 0
b10100 *
1)
b1001 %
#110000
0$
#115000
1$
#116000
1&
b10110 *
0)
#117000
b10111 *
#120000
0$
#125000
0"
b10 !
b10 ,
b1 .
1$
#126000
b1 1
b11001 *
1&
#127000
b11010 *
#130000
0$
#135000
b11 !
b11 ,
b10 .
1$
#136000
b10 1
b11100 *
1&
#137000
b11101 *
#140000
0$
#145000
b100 !
b100 ,
b11 .
1$
#146000
b11 1
b11111 *
1&
#147000
b100000 *
#150000
0$
#155000
b101 !
b101 ,
b100 .
1$
#156000
b100 1
b100010 *
1&
#157000
b100011 *
#160000
0$
#165000
b110 !
b110 ,
b101 .
1$
#166000
b101 1
b100101 *
1&
#167000
b100110 *
#170000
0$
#175000
b111 !
b111 ,
b110 .
1$
#176000
b110 1
b101000 *
1&
#177000
b101001 *
#180000
0$
#185000
b1000 !
b1000 ,
b111 .
1$
#186000
b111 1
b101011 *
1&
#187000
b101100 *
#190000
0$
#195000
b1 !
b1 ,
1#
b1000 .
1$
#196000
b1000 1
b101110 *
1&
#200000
0$
#205000
1$
#206000
1)
b110000 *
0&
#210000
0$
#215000
0#
b1001 /
b1001 !
b1001 ,
1$
#216000
b1010 (
b1010 -
b1 2
b110010 *
1)
b1010 %
#220000
0$
#225000
b1010 /
1$
#226000
b1011 (
b1011 -
b10 2
b110100 *
1)
b1011 %
#230000
0$
#235000
b1011 /
1$
#236000
b1100 (
b1100 -
b11 2
b110110 *
1)
b1100 %
#240000
0$
#245000
b1100 /
1$
#246000
b1101 (
b1101 -
b100 2
b111000 *
1)
b1101 %
#250000
0$
#255000
b1101 /
1$
#256000
1&
b101 2
b111010 *
0)
b1110 %
#257000
b111011 *
#260000
0$
#265000
b1010 !
b1010 ,
b1001 .
1$
#266000
b1 3
b111101 *
1&
#267000
b111110 *
#270000
0$
#275000
b1011 !
b1011 ,
b1010 .
1$
#276000
b10 3
b1000000 *
1&
#277000
b1000001 *
#280000
0$
#285000
b1100 !
b1100 ,
b1011 .
1$
#286000
1)
b1110 (
b1110 -
b11 3
b1000011 *
0&
#290000
0$
#295000
b1110 /
1$
#296000
b1111 (
b1111 -
b1 4
b1000101 *
1)
b1111 %
#300000
0$
#305000
b1111 /
1$
#306000
b10000 (
b10000 -
b10 4
b1000111 *
1)
b10000 %
#310000
0$
#315000
b0 /
1$
#316000
b10001 (
b10001 -
b11 4
b1001001 *
1)
b10001 %
#320000
0$
#325000
b1 /
1$
#326000
b10010 (
b10010 -
b100 4
b1001011 *
1)
b10010 %
#330000
0$
#335000
b10 /
1$
#336000
b10011 (
b10011 -
b101 4
b1001101 *
1)
b10011 %
#340000
0$
#345000
1"
b11 /
1$
#346000
1&
b110 4
b1001111 *
0)
b10100 %
#347000
b1010000 *
#350000
0$
#355000
0"
b1101 !
b1101 ,
b1100 .
1$
#356000
b1010010 *
1&
#357000
b1010011 *
#360000
0$
#365000
b1110 !
b1110 ,
b1101 .
1$
#366000
b1010101 *
1&
#367000
b1010110 *
#370000
0$
#375000
b1111 !
b1111 ,
b1110 .
1$
#376000
b1011000 *
1&
#377000
b1011001 *
#380000
0$
#385000
b10000 !
b10000 ,
b1111 .
1$
#386000
b1011011 *
1&
#387000
b1011100 *
#390000
0$
#395000
b10001 !
b10001 ,
b0 .
1$
#396000
b1011110 *
1&
#397000
b1011111 *
#400000
0$
#405000
b10010 !
b10010 ,
b1 .
1$
#406000
b1100001 *
1&
#407000
b1100010 *
#410000
0$
#415000
b10011 !
b10011 ,
b10 .
1$
#416000
b1100100 *
1&
#417000
b1100101 *
#420000
0$
#425000
b1100 !
b1100 ,
1#
b11 .
1$
#426000
1)
b10100 (
b10100 -
b1100111 *
0&
#430000
0$
#435000
0#
b100 /
b10100 !
b10100 ,
1$
#436000
1&
b10101 (
b10101 -
b1101001 *
1)
b10101 %
#437000
b1101010 *
#440000
0$
#445000
b10101 !
b10101 ,
b101 /
0#
b100 .
1$
#446000
b10110 (
b10110 -
b1 5
b1101100 *
1&
1)
b10110 %
#447000
b1101101 *
#450000
0$
#455000
b10110 !
b10110 ,
b101 .
b110 /
1$
#456000
b10111 (
b10111 -
b10 5
b1101111 *
1&
1)
b10111 %
#457000
b1110000 *
#460000
0$
#465000
b10111 !
b10111 ,
b111 /
0#
b110 .
1$
#466000
b11000 (
b11000 -
b11 5
b1110010 *
1&
1)
b11000 %
#467000
b1110011 *
#470000
0$
#475000
b11000 !
b11000 ,
b111 .
b1000 /
1$
#476000
b11001 (
b11001 -
b100 5
b1110101 *
1&
1)
b11001 %
#477000
b1110110 *
#480000
0$
#485000
b11001 !
b11001 ,
b1001 /
0#
b1000 .
1$
#486000
b11010 (
b11010 -
b101 5
b1111000 *
1&
1)
b11010 %
#487000
b1111001 *
#490000
0$
#495000
b11010 !
b11010 ,
b1001 .
b1010 /
1$
#496000
b11011 (
b11011 -
b110 5
b1111011 *
1&
1)
b11011 %
#497000
b1111100 *
#500000
0$
#505000
b11011 !
b11011 ,
b1011 /
0#
b1010 .
1$
#506000
b11100 (
b11100 -
b111 5
b1111110 *
1&
1)
b11100 %
#507000
b1111111 *
#510000
0$
#515000
b11100 !
b11100 ,
b1011 .
b1100 /
1$
#516000
b11101 (
b11101 -
b1000 5
b10000001 *
1&
1)
b11101 %
#517000
b10000010 *
#520000
0$
#525000
b11101 !
b11101 ,
b1101 /
0#
b1100 .
1$
#526000
b11110 (
b11110 -
b1001 5
b10000100 *
1&
1)
b11110 %
#527000
b10000101 *
#530000
0$
#535000
b11110 !
b11110 ,
b1101 .
b1110 /
1$
#536000
b1010 5
b10000111 *
1&
0)
b11111 %
#537000
b10001000 *
#540000
0$
#545000
b10111 !
b10111 ,
1#
b1110 .
1$
#546000
b10001010 *
0&
