examples/phase4_uvm_python/alu_if_and_dut.sv
//------------------------------------------------------------------------
// alu_if_and_dut.sv
//
// Phase 2 example: SystemVerilog data types + interfaces/modports.
//
// Demonstrates, in one small self-contained design:
//   - a packed enum type for the ALU opcode (readable in waveforms,
//     unlike a bare 3-bit code, and gives the compiler/simulator a
//     restricted value set to catch typos)
//   - a packed struct bundling the ALU result's status flags
//     (zero/carry/overflow) as a single typed object instead of three
//     loose wires
//   - an `interface` bundling the DUT<->testbench connection, with two
//     `modport`s (`dut` and `tb`) giving each side a *direction-checked*
//     view of the same signals -- the idiomatic reason to use an
//     interface at all
//
// TOOLING NOTES (found this session, 2026-08-24, all against the
// Icarus Verilog 10.3 build this repo's tools/setup_iverilog.sh
// installs -- see that script and the 2026-08-23 AUTOMATION_LOG.md
// entry for the two gaps found that day; this session found several
// more, all confirmed with minimal standalone repros before working
// around them here, so these are real toolchain limits, not bugs in
// this file's logic):
//
//   1. Interfaces cannot be used as module ports at all, in any syntax
//      form (`alu_if.dut vif`, `alu_if vif`, ANSI or non-ANSI style;
//      tried all four with `-g2012` and `-g2005-sv`) -- every form fails
//      with the same "Errors in port declarations" syntax error, even
//      for a two-line minimal interface with no modports. The interface
//      *declaration* below (with modports) compiles cleanly on its own;
//      it just cannot be used to type a module port on this build.
//   2. `always_comb` does not compile at all on this build, in any form
//      (single-statement or `begin/end` block), even completely
//      standalone with no ports, structs, or enums involved. Confirmed
//      with a 3-line minimal repro. `always_ff` likewise does not
//      compile (minimal repro: a 4-line register with async reset).
//      Plain Verilog-2001-style `always @*` and
//      `always @(posedge clk or negedge rst_n)` -- the style already
//      used throughout this repo's Phase 1 examples -- work fine and are
//      used below instead.
//   3. `unique case` / `priority case` do not compile; plain `case` (as
//      already used in Phase 1) works and is used below.
//   4. SystemVerilog assignment-pattern syntax (`'{default: 1'b0}`,
//      `'0` fill) does not compile for a packed-struct target; per-field
//      assignment (`flags.zero <= 1'b0;` etc.) works and is used below.
//
// Given (1)-(4), this Icarus 10.3 build's practical SystemVerilog support
// is closer to "Verilog-2001 plus typedef enum/struct and interface/
// always @* declarations" than to full IEEE 1800-2017 support -- useful
// to know heading into the rest of Phase 2 (classes, randomization,
// coverage are all *more* advanced SV than any of the above, so those
// examples should be spot-checked early too rather than assumed to
// compile, exactly as the 2026-08-23 log entry already anticipated).
// Because of (1), `alu_dut` below uses a plain (non-interface) port
// list -- see alu_if_tb.sv's header for how it is still connected
// through the `alu_if` interface instance via a named port map, and
// AUTOMATION_LOG.md (2026-08-24 entry) for the full summary.
//------------------------------------------------------------------------

`timescale 1ns/1ps

// 4-value packed enum -- default base type is `int` (2-state, 32-bit) but
// as a *port/interface field* it participates in the interface's 4-state
// `logic` signals, so X propagation still works if the DUT is unresolved
// or reset is not yet applied. Named values are far more readable than
// a bare 3'b010 in a waveform viewer or testbench trace.
typedef enum logic [2:0] {
    ALU_ADD = 3'b000,
    ALU_SUB = 3'b001,
    ALU_AND = 3'b010,
    ALU_OR  = 3'b011,
    ALU_XOR = 3'b100
} alu_op_e;

// Packed struct: bundles the three status flags into one typed field
// instead of three separate 1-bit ports. Packed (not just a SV struct)
// so it behaves like a single vector for waveform/VCD purposes and can
// be compared/assigned as a unit.
typedef struct packed {
    logic zero;
    logic carry;
    logic overflow;
} alu_flags_s;

// Interface bundling the full DUT<->TB connection for an 8-bit ALU.
// Using `logic` (not `wire`/`reg`) throughout, per SV convention, since
// `logic` can be driven by either continuous assignment or a procedural
// block and the simulator enforces single-driver rules regardless.
//
// See TOOLING NOTE (1) above: this interface's declaration compiles
// cleanly on Icarus 10.3 (verified); it is only *using it as a module
// port* (with or without a modport qualifier) that this build rejects.
// The modports below are the idiomatically-correct direction-checked
// views each side would use as its port type on a simulator with full
// interface-port support.
interface alu_if (input logic clk, input logic rst_n);
    logic  [7:0]   a, b;
    alu_op_e       op;
    logic          valid;
    logic  [7:0]   result;
    alu_flags_s    flags;
    logic          result_valid;

    // Intended DUT-side view (not usable as a port on this Icarus build
    // -- see TOOLING NOTE (1)): DUT reads stimulus fields as inputs,
    // drives result fields as outputs.
    modport dut (
        input  clk, rst_n, a, b, op, valid,
        output result, flags, result_valid
    );

    // Intended TB-side view (likewise not usable as a port here): mirror
    // image of the dut modport, from the same single point of
    // definition -- the value of interfaces over a raw port list is
    // that both sides' views are generated from one declaration instead
    // of two independently hand-maintained port lists that can silently
    // drift out of sync.
    modport tb (
        input  clk, rst_n, result, flags, result_valid,
        output a, b, op, valid
    );
endinterface

// Synchronous ALU DUT. Plain (non-interface) port list -- see TOOLING
// NOTE (1) above for why; this is the workaround for Icarus 10.3's lack
// of interface-port support, not the intended final form. Registers its
// inputs and result one cycle later (a deliberately simple pipeline
// stage, not purely combinational) so the example also exercises
// `result_valid` as a one-cycle-delayed valid signal -- a common real
// pattern the testbench must handle correctly.
module alu_dut (
    input  logic        clk,
    input  logic        rst_n,
    input  logic [7:0]  a,
    input  logic [7:0]  b,
    input  alu_op_e     op,
    input  logic        valid,
    output logic [7:0]  result,
    output alu_flags_s  flags,
    output logic        result_valid
);

    logic [7:0]  result_c;
    alu_flags_s  flags_c;
    logic [8:0]  add_ext, sub_ext; // 9-bit to catch carry/borrow

    // Combinational compute stage. Plain `always @*` -- see TOOLING
    // NOTE (2): `always_comb` does not compile on this Icarus build.
    always @* begin
        add_ext = {1'b0, a} + {1'b0, b};
        sub_ext = {1'b0, a} - {1'b0, b};

        // Plain `case` -- see TOOLING NOTE (3): `unique case` does not
        // compile on this Icarus build.
        case (op)
            ALU_ADD: result_c = add_ext[7:0];
            ALU_SUB: result_c = sub_ext[7:0];
            ALU_AND: result_c = a & b;
            ALU_OR:  result_c = a | b;
            ALU_XOR: result_c = a ^ b;
            default: result_c = 8'hxx; // unreachable given alu_op_e's
                                        // restricted value set, but kept
                                        // as an explicit safety default
        endcase

        flags_c.zero     = (result_c == 8'h00);
        flags_c.carry    = (op == ALU_ADD) ? add_ext[8] :
                            (op == ALU_SUB) ? sub_ext[8] : 1'b0;
        // Signed overflow: both operands same sign, result different sign
        // (only meaningful for ADD/SUB; 0 for logical ops)
        flags_c.overflow =
            (op == ALU_ADD) ? ((a[7] == b[7]) && (result_c[7] != a[7])) :
            (op == ALU_SUB) ? ((a[7] != b[7]) && (result_c[7] != a[7])) :
            1'b0;
    end

    // Registered (1-cycle-latency) output stage. Plain
    // `always @(posedge clk or negedge rst_n)` -- see TOOLING NOTE (2):
    // `always_ff` does not compile on this Icarus build. Per-field
    // struct reset assignment -- see TOOLING NOTE (4): the
    // `'{default: 1'b0}` assignment-pattern syntax does not compile on
    // this Icarus build.
    always @(posedge clk or negedge rst_n) begin
        if (!rst_n) begin
            result          <= 8'h00;
            flags.zero      <= 1'b0;
            flags.carry     <= 1'b0;
            flags.overflow  <= 1'b0;
            result_valid    <= 1'b0;
        end else begin
            result       <= result_c;
            flags        <= flags_c;
            result_valid <= valid;
        end
    end

endmodule

examples/phase2/alu_manual_constrained_random.sv
//------------------------------------------------------------------------
// alu_manual_constrained_random.sv
//
// Phase 2 example: "Randomization (rand/randc, constraints, randomize(),
// dist)" -- the next progress.md item after OOP testbench components
// (2026-08-25). Reuses alu_dut from alu_if_and_dut.sv unmodified, exactly
// as alu_oop_tb_components.sv already does.
//
// TOOLING FINDING (this session, 2026-08-26, confirmed with minimal
// standalone repros before being treated as established -- see
// notes/2026-08-26-randomization-rand-randc-constraints.md, Section 2,
// for full detail and repro listings): this Icarus Verilog 10.3 build
// has NO constrained-random support at all -- `randomize()` is not
// implemented for any class ("No function named `f.randomize' found in
// this context"), and `constraint`/`inside`/`dist` are all explicitly
// rejected by the parser ("sorry: ... not supported yet"). This is a
// materially bigger gap than the missing SV *pieces* found on
// 2026-08-23/24/25 (those had usable in-language workarounds); native
// constrained-random simply is not present on this build.
//
// This file therefore demonstrates the SAME CONCEPTS (uniform random
// fields, `randc`-like guaranteed-cyclic coverage of a small corner-case
// set, `dist`-like weighted biasing toward an interesting corner) via
// hand-written $urandom_range-based equivalents, clearly documented as a
// workaround, not presented as if it were real constraint solving (see
// notes/2026-08-26-*.md, Section 3, for why this equivalence holds for
// the specific simple constraints used here but would NOT scale to
// correlated multi-field constraints -- exactly why real tools implement
// a solver instead of leaving this to hand-written code).
//
// TWO FURTHER TOOLING GAPS found and worked around while building this
// file (both new today, both confirmed with minimal repros -- see
// notes/2026-08-26-*.md, Section 2a and the two additional findings
// below, not yet in that file's initial gap list but consistent with the
// same investigate-before-committing practice):
//
//   - `Foo f = new();` (inline declare+construct) does not parse on this
//     build; the working form is the two-statement `Foo f; f = new();`
//     already used (by necessity, it turns out) throughout this repo's
//     prior class examples.
//   - Calling a `function void` (or any function whose return value is
//     discarded, i.e. invoked "as a task") from WITHIN another class
//     task/function crashes the elaborator
//     ("assert: elab_expr.cc:1257: failed assertion 0"), even though the
//     identical call works fine from a top-level `initial` block. Only
//     task-calling-task (not function-calling-function-as-statement)
//     is safe inside a class method body.
//   - Unpacked fixed-size arrays (`logic [7:0] vals[0:4];`) as CLASS
//     PROPERTIES are fundamentally broken on this build -- both
//     assigning to an indexed element from within a class method and
//     indexing into one from outside the class crash (two different
//     assertions: a codegen-time `stmt_assign.c` assertion and an
//     elaboration-time `elaborate.cc` assertion respectively). SV queues
//     as class properties are also explicitly rejected
//     ("sorry: SV queues inside classes are not yet supported").
//     Module-level (non-class) unpacked arrays work fine (already used,
//     e.g., for `sync_fifo.v`'s memory array) -- so the randc-like
//     corner-value queue and the dist-like weighted-opcode picker below
//     are implemented as plain MODULE-LEVEL tasks operating on a
//     module-level array, not as class methods/properties. This is a
//     genuine design constraint on this simulator, not a style choice --
//     documented here so a future session doesn't rediscover it from
//     scratch, exactly as this repo's established practice requires.
//------------------------------------------------------------------------

`timescale 1ns/1ps

module alu_manual_constrained_random_tb;

    // ---- Transaction: encapsulates one ALU stimulus item ----
    // Plain `logic [2:0]` for op (not `alu_op_e`), per the established
    // enum-in-class-context workaround already used in alu_oop_tb_components.sv.
    class alu_transaction;
        logic [7:0] a, b;
        logic [2:0] op_raw;

        function string op_name();
            case (op_raw)
                3'b000: op_name = "ALU_ADD";
                3'b001: op_name = "ALU_SUB";
                3'b010: op_name = "ALU_AND";
                3'b011: op_name = "ALU_OR";
                3'b100: op_name = "ALU_XOR";
                default: op_name = "ALU_?";
            endcase
        endfunction
    endclass

    // ---- Scoreboard: independent reference model + pass/fail tracking ----
    // Identical structure/logic to alu_oop_tb_components.sv's scoreboard
    // (same DUT, same independent reference model) -- reused unmodified
    // here since today's new content is the *generation* side, not the
    // checking side.
    class alu_scoreboard;
        int checks = 0;
        int errors = 0;

        task predict(input logic [7:0] a, b, input logic [2:0] op_raw,
                     output logic [7:0] exp_result, output alu_flags_s exp_flags);
            logic [8:0] add_ext, sub_ext;
            add_ext = {1'b0, a} + {1'b0, b};
            sub_ext = {1'b0, a} - {1'b0, b};
            case (op_raw)
                3'b000: exp_result = add_ext[7:0];
                3'b001: exp_result = sub_ext[7:0];
                3'b010: exp_result = a & b;
                3'b011: exp_result = a | b;
                3'b100: exp_result = a ^ b;
                default: exp_result = 8'hxx;
            endcase
            exp_flags.zero  = (exp_result == 8'h00);
            exp_flags.carry = (op_raw == 3'b000) ? add_ext[8] :
                               (op_raw == 3'b001) ? sub_ext[8] : 1'b0;
            exp_flags.overflow =
                (op_raw == 3'b000) ? ((a[7] == b[7]) && (exp_result[7] != a[7])) :
                (op_raw == 3'b001) ? ((a[7] != b[7]) && (exp_result[7] != a[7])) :
                1'b0;
        endtask

        task check(input logic [7:0] a, b, input logic [2:0] op_raw,
                   input logic [7:0] actual_result, input alu_flags_s actual_flags,
                   input logic actual_result_valid, input int idx, input string opname,
                   input bit is_corner);
            logic [7:0] exp_result;
            alu_flags_s exp_flags;
            predict(a, b, op_raw, exp_result, exp_flags);
            checks = checks + 1;
            if (actual_result_valid !== 1'b1) begin
                errors = errors + 1;
                $display("FAIL [txn %0d, %s%s]: result_valid=%b, expected 1",
                          idx, opname, is_corner ? " CORNER" : "", actual_result_valid);
            end else if (actual_result !== exp_result) begin
                errors = errors + 1;
                $display("FAIL [txn %0d, %s%s]: result=%0d, expected %0d",
                          idx, opname, is_corner ? " CORNER" : "", actual_result, exp_result);
            end else if (actual_flags !== exp_flags) begin
                errors = errors + 1;
                $display("FAIL [txn %0d, %s%s]: flags={z,c,ovf}=%b, expected %b",
                          idx, opname, is_corner ? " CORNER" : "", actual_flags, exp_flags);
            end else begin
                $display("PASS [txn %0d, %s%s]: a=%0d b=%0d result=%0d flags={z,c,ovf}=%b",
                          idx, opname, is_corner ? " CORNER" : "", a, b, actual_result, actual_flags);
            end
        endtask

        function void report();
            $display("------------------------------------------------------");
            $display("alu_scoreboard: %0d checks, %0d errors", checks, errors);
            if (errors == 0)
                $display("RESULT: ALL CHECKS PASSED");
            else
                $display("RESULT: %0d CHECK(S) FAILED", errors);
            $display("------------------------------------------------------");
        endfunction
    endclass

    // ---- Manual "randc"-like corner-value picker (module-level, see
    // header note on why this cannot live inside a class on this build) ----
    // Guarantees each of the 5 chosen corner values (0x00, 0xFF, 0x80,
    // 0x7F, 0x01 -- the classic unsigned/signed 8-bit boundary values)
    // appears exactly once per shuffled cycle before any repeats, which
    // is the defining behavior of SystemVerilog's `randc` -- implemented
    // here via a manual Fisher-Yates shuffle + pointer, not rejection
    // sampling, so the "exactly once per cycle" guarantee holds by
    // construction rather than probabilistically.
    logic [7:0] corner_vals[0:4];
    int         corner_ptr;

    task shuffle_corners();
        int j;
        logic [7:0] tmp;
        for (int i = 4; i > 0; i = i - 1) begin
            j = $urandom_range(0, i);
            tmp = corner_vals[i];
            corner_vals[i] = corner_vals[j];
            corner_vals[j] = tmp;
        end
        corner_ptr = 0;
    endtask

    task next_corner_value(output logic [7:0] v);
        if (corner_ptr >= 5) shuffle_corners();
        v = corner_vals[corner_ptr];
        corner_ptr = corner_ptr + 1;
    endtask

    // ---- Manual "dist"-like weighted opcode picker (module-level) ----
    // Emulates `op_raw dist {ALU_SUB := 3, [ALU_ADD:ALU_XOR] :/ 1}` --
    // ALU_SUB gets 3/7 of the weight (~43%) instead of the 1/5 (20%) a
    // uniform pick would give, biasing generation toward SUB because its
    // borrow/overflow flag logic is the ALU's most bug-prone corner (see
    // notes/2026-08-22-combinational-and-sequential-logic-review.md).
    // Implemented as the standard manual technique for weighted random
    // choice: a cumulative-weight table and a single $urandom_range draw
    // against it.
    task weighted_op_select(output logic [2:0] op_raw);
        int r;
        r = $urandom_range(0, 6);           // 7 = 1(ADD)+3(SUB)+1(AND)+1(OR)+1(XOR)
        if (r < 1)      op_raw = 3'b000;    // ALU_ADD: r=0            (1/7)
        else if (r < 4) op_raw = 3'b001;    // ALU_SUB: r=1,2,3        (3/7)
        else if (r < 5) op_raw = 3'b010;    // ALU_AND: r=4            (1/7)
        else if (r < 6) op_raw = 3'b011;    // ALU_OR:  r=5            (1/7)
        else            op_raw = 3'b100;    // ALU_XOR: r=6            (1/7)
    endtask

    logic clk = 0;
    logic rst_n;
    always #5 clk = ~clk; // 100 MHz

    logic [7:0] a, b, result;
    logic [2:0] op_raw;
    logic       valid, result_valid;
    alu_flags_s flags;

    alu_dut dut (
        .clk          (clk),
        .rst_n        (rst_n),
        .a            (a),
        .b            (b),
        .op           (op_raw),
        .valid        (valid),
        .result       (result),
        .flags        (flags),
        .result_valid (result_valid)
    );

    alu_scoreboard sb;

    localparam int NUM_TRANSACTIONS = 20;   // 20 = 4*5: exactly one full
                                             // corner-queue cycle worth of
                                             // corner draws (one every 4th
                                             // transaction), so the
                                             // histogram at the end can
                                             // show all 5 corners hit
                                             // exactly once.

    initial begin
        alu_transaction t;
        logic [7:0] sent_a, sent_b;
        logic [2:0] sent_op;
        bit         is_corner;
        int         op_hist[0:4];
        int         corner_hits[0:4];
        int         corner_idx;

        $dumpfile("alu_manual_constrained_random_wave.vcd");
        $dumpvars(0, alu_manual_constrained_random_tb);

        corner_vals[0] = 8'h00;
        corner_vals[1] = 8'hFF;
        corner_vals[2] = 8'h80;
        corner_vals[3] = 8'h7F;
        corner_vals[4] = 8'h01;
        corner_ptr = 5;   // force a shuffle before the first draw

        sb = new();

        rst_n = 0; a = 0; b = 0; op_raw = 0; valid = 0;
        repeat (3) @(posedge clk);
        rst_n = 1;
        @(posedge clk);

        for (int i = 0; i < NUM_TRANSACTIONS; i++) begin
            // "Generator" step: manual constrained-random fill (see
            // header note -- no native randomize()/constraint on this
            // build). b is uniform over the full 8-bit range (the
            // trivial case a real solver would also reduce to for an
            // unconstrained field); op_raw is dist-like weighted toward
            // SUB; a is uniform EXCEPT every 4th transaction, where it
            // is drawn from the randc-like corner-value queue instead.
            t = new();
            t.b = $urandom_range(0, 255);
            weighted_op_select(sent_op);
            t.op_raw = sent_op;
            op_hist[sent_op] = op_hist[sent_op] + 1;

            if ((i % 4) == 3) begin
                next_corner_value(sent_a);
                t.a = sent_a;
                is_corner = 1;
                case (sent_a)
                    8'h00: corner_hits[0] = corner_hits[0] + 1;
                    8'hFF: corner_hits[1] = corner_hits[1] + 1;
                    8'h80: corner_hits[2] = corner_hits[2] + 1;
                    8'h7F: corner_hits[3] = corner_hits[3] + 1;
                    8'h01: corner_hits[4] = corner_hits[4] + 1;
                endcase
            end else begin
                sent_a = $urandom_range(0, 255);
                t.a = sent_a;
                is_corner = 0;
            end
            sent_b = t.b;

            // "Driver" step: apply to DUT pins (procedural -- no
            // interface-port support on this build, per
            // alu_if_and_dut.sv's TOOLING NOTE 1).
            a <= sent_a; b <= sent_b; op_raw <= sent_op; valid <= 1'b1;
            @(posedge clk);
            valid <= 1'b0;
            @(posedge clk); // wait for the 1-cycle registered DUT latency

            // "Monitor" + "scoreboard" step.
            sb.check(sent_a, sent_b, sent_op, result, flags, result_valid,
                      i, t.op_name(), is_corner);
        end

        sb.report();
        $display("op_raw histogram: ADD=%0d SUB=%0d AND=%0d OR=%0d XOR=%0d (expect SUB notably above uniform ~%0d/%0d each)",
                  op_hist[0], op_hist[1], op_hist[2], op_hist[3], op_hist[4],
                  NUM_TRANSACTIONS, 5);
        $display("corner-value coverage (5 corners, %0d draws): 0x00=%0d 0xFF=%0d 0x80=%0d 0x7F=%0d 0x01=%0d (expect each exactly 1, one full randc-like cycle)",
                  NUM_TRANSACTIONS/4,
                  corner_hits[0], corner_hits[1], corner_hits[2],
                  corner_hits[3], corner_hits[4]);

        $finish;
    end

endmodule

examples/phase2/alu_manual_constrained_random_wave.vcd
$date
	Wed Aug 26 04:56:14 2026
$end
$version
	Icarus Verilog
$end
$timescale
	1ps
$end
$scope module alu_manual_constrained_random_tb $end
$var wire 1 ! result_valid $end
$var wire 8 " result [7:0] $end
$var wire 3 # flags [2:0] $end
$var reg 8 $ a [7:0] $end
$var reg 8 % b [7:0] $end
$var reg 1 & clk $end
$var reg 3 ' op_raw [2:0] $end
$var reg 1 ( rst_n $end
$var reg 1 ) valid $end
$var integer 32 * corner_ptr [31:0] $end
$scope module dut $end
$var wire 8 + a [7:0] $end
$var wire 8 , b [7:0] $end
$var wire 1 & clk $end
$var wire 3 - op [2:0] $end
$var wire 1 ( rst_n $end
$var wire 1 ) valid $end
$var reg 9 . add_ext [8:0] $end
$var reg 3 / flags [2:0] $end
$var reg 3 0 flags_c [2:0] $end
$var reg 8 1 result [7:0] $end
$var reg 8 2 result_c [7:0] $end
$var reg 1 ! result_valid $end
$var reg 9 3 sub_ext [8:0] $end
$upscope $end
$scope begin $unm_blk_10 $end
$var reg 8 4 sent_a [7:0] $end
$var reg 8 5 sent_b [7:0] $end
$var reg 3 6 sent_op [2:0] $end
$var reg 1 7 is_corner $end
$scope begin $ivl_for_loop1 $end
$var integer 32 8 i [31:0] $end
$upscope $end
$upscope $end
$scope task next_corner_value $end
$var reg 8 9 v [7:0] $end
$upscope $end
$scope task shuffle_corners $end
$var reg 8 : tmp [7:0] $end
$var integer 32 ; j [31:0] $end
$scope begin $ivl_for_loop0 $end
$var integer 32 < i [31:0] $end
$upscope $end
$upscope $end
$scope task weighted_op_select $end
$var reg 3 = op_raw [2:0] $end
$var integer 32 > r [31:0] $end
$upscope $end
$upscope $end
$enddefinitions $end
#0
$dumpvars
b0 >
bx =
b0 <
b0 ;
bx :
bx 9
b0 8
07
bx 6
bx 5
bx 4
b0 3
b0 2
b0 1
b100 0
b0 /
b0 .
b0 -
b0 ,
b0 +
b101 *
0)
0(
b0 '
0&
b0 %
b0 $
b0 #
b0 "
0!
$end
#5000
1&
#10000
0&
#15000
1&
#20000
0&
#25000
b100 #
b100 /
1(
1&
#30000
0&
#35000
b10 0
b1110010 2
b101110010 3
b10010110 .
1)
b1 '
b1 -
b10010010 %
b10010010 ,
b100 $
b100 +
b10010010 5
b100 4
b1 6
b1 =
b1 >
1&
#40000
0&
#45000
1!
b10 #
b10 /
b1110010 "
b1110010 1
0)
1&
#50000
0&
#55000
b0 0
b10010101 2
b10010101 3
b11110111 .
0!
1)
b110001 %
b110001 ,
b11000110 $
b11000110 +
b110001 5
b11000110 4
b11 >
b1 8
1&
#60000
0&
#65000
1!
b0 #
b0 /
b10010101 "
b10010101 1
0)
1&
#70000
0&
#75000
b10110010 2
b1001110 3
b10110010 .
0!
1)
b0 '
b0 -
b110010 %
b110010 ,
b10000000 $
b10000000 +
b110010 5
b10000000 4
b0 6
b0 =
b0 >
b10 8
1&
#80000
0&
#85000
1!
b10110010 "
b10110010 1
0)
1&
#90000
0&
#95000
b10000110 2
b101111010 3
b10000110 .
0!
1)
b11 '
b11 -
b10000110 %
b10000110 ,
b0 $
b0 +
b10000110 5
17
b0 4
b0 9
b1 *
b11111111 :
b1 ;
b0 <
b11 6
b11 =
b101 >
b11 8
1&
#100000
0&
#105000
1!
b10000110 "
b10000110 1
0)
1&
#110000
0&
#115000
b10 0
b11110010 2
b111110010 3
b10111000 .
0!
1)
b1 '
b1 -
b1100011 %
b1100011 ,
b1010101 $
b1010101 +
b1100011 5
07
b1010101 4
b1 6
b1 =
b10 >
b100 8
1&
#120000
0&
#125000
1!
b10 #
b10 /
b11110010 "
b11110010 1
0)
1&
#130000
0&
#135000
b10111 2
b100010111 3
b11111011 .
0!
1)
b11110010 %
b11110010 ,
b1001 $
b1001 +
b11110010 5
b1001 4
b1 >
b101 8
1&
#140000
0&
#145000
1!
b10111 "
b10111 1
0)
1&
#150000
0&
#155000
b0 0
b10100000 2
b110100000 3
b100101110 .
0!
1)
b100 '
b100 -
b11000111 %
b11000111 ,
b1100111 $
b1100111 +
b11000111 5
b1100111 4
b100 6
b100 =
b110 >
b110 8
1&
#160000
0&
#165000
1!
b0 #
b0 /
b10100000 "
b10100000 1
0)
1&
#170000
0&
#175000
b10001011 2
b10001011 3
b101110011 .
0!
1)
b1 '
b1 -
b1110100 %
b1110100 ,
b11111111 $
b11111111 +
b1110100 5
17
b11111111 4
b10 *
b11111111 9
b1 6
b1 =
b10 >
b111 8
1&
#180000
0&
#185000
1!
b10001011 "
b10001011 1
0)
1&
#190000
0&
#195000
b10 0
b1101000 2
b101101000 3
b11000100 .
0!
1)
b10101110 %
b10101110 ,
b10110 $
b10110 +
b10101110 5
07
b10110 4
b1000 8
1&
#200000
0&
#205000
1!
b10 #
b10 /
b1101000 "
b1101000 1
0)
1&
#210000
0&
#215000
b1 0
b1010011 2
b1010011 3
b10110111 .
0!
1)
b110010 %
b110010 ,
b10000101 $
b10000101 +
b110010 5
b10000101 4
b1 >
b1001 8
1&
#220000
0&
#225000
1!
b1 #
b1 /
b1010011 "
b1010011 1
0)
1&
#230000
0&
#235000
b0 0
b10010101 2
b10010101 3
b100010101 .
0!
1)
b1000000 %
b1000000 ,
b11010101 $
b11010101 +
b1000000 5
b11010101 4
b11 >
b1010 8
1&
#240000
0&
#245000
1!
b0 #
b0 /
b10010101 "
b10010101 1
0)
1&
#250000
0&
#255000
b1 0
b110010 2
b110010 3
b11001110 .
0!
1)
b1001110 %
b1001110 ,
b10000000 $
b10000000 +
b1001110 5
17
b10000000 4
b11 *
b10000000 9
b10 >
b1011 8
1&
#260000
0&
#265000
1!
b1 #
b1 /
b110010 "
b110010 1
0)
1&
#270000
0&
#275000
b0 0
b100000 3
b110010 .
0!
1)
b0 '
b0 -
b1001 %
b1001 ,
b101001 $
b101001 +
b1001 5
07
b101001 4
b0 6
b0 =
b0 >
b1100 8
1&
#280000
0&
#285000
1!
b0 #
b0 /
0)
1&
#290000
0&
#295000
b10 0
b1001100 2
b101001100 3
b10110110 .
0!
1)
b1 '
b1 -
b10110101 %
b10110101 ,
b1 $
b1 +
b10110101 5
b1 4
b1 6
b1 =
b10 >
b1101 8
1&
#300000
0&
#305000
1!
b10 #
b10 /
b1001100 "
b1001100 1
0)
1&
#310000
0&
#315000
b0 0
b10000 2
b10000 3
b10111110 .
0!
1)
b1010111 %
b1010111 ,
b1100111 $
b1100111 +
b1010111 5
b1100111 4
b11 >
b1110 8
1&
#320000
0&
#325000
1!
b0 #
b0 /
b10000 "
b10000 1
0)
1&
#330000
0&
#335000
b10 0
b1110000 2
b101110000 3
b10010010 .
0!
1)
b10010001 %
b10010001 ,
b1 $
b1 +
b10010001 5
17
b1 4
b100 *
b1 9
b1111 8
1&
#340000
0&
#345000
1!
b10 #
b10 /
b1110000 "
b1110000 1
0)
1&
#350000
0&
#355000
b1011110 2
b10010100 3
b101011110 .
0!
1)
b0 '
b0 -
b1100101 %
b1100101 ,
b11111001 $
b11111001 +
b1100101 5
07
b11111001 4
b0 6
b0 =
b0 >
b10000 8
1&
#360000
0&
#365000
1!
b1011110 "
b1011110 1
0)
1&
#370000
0&
#375000
b0 0
b1000100 2
b110100111 3
b100110001 .
0!
1)
b10 '
b10 -
b11000101 %
b11000101 ,
b1101100 $
b1101100 +
b11000101 5
b1101100 4
b10 6
b10 =
b100 >
b10001 8
1&
#380000
0&
#385000
1!
b0 #
b0 /
b1000100 "
b1000100 1
0)
1&
#390000
0&
#395000
b111001 2
b111001 3
b110110001 .
0!
1)
b1 '
b1 -
b10111100 %
b10111100 ,
b11110101 $
b11110101 +
b10111100 5
b11110101 4
b1 6
b1 =
b1 >
b10010 8
1&
#400000
0&
#405000
1!
b111001 "
b111001 1
0)
1&
#410000
0&
#415000
b10100100 2
b110100100 3
b101011010 .
0!
1)
b100 '
b100 -
b11011011 %
b11011011 ,
b1111111 $
b1111111 +
b11011011 5
17
b1111111 4
b101 *
b1111111 9
b100 6
b100 =
b110 >
b10011 8
1&
#420000
0&
#425000
1!
b10100100 "
b10100100 1
0)
1&
#430000
0&
#435000
0!
b10100 8
1&
