examples/phase4_uvm_python/alu_if_and_dut.sv
//------------------------------------------------------------------------
// alu_if_and_dut.sv
//
// Phase 2 example: SystemVerilog data types + interfaces/modports.
//
// Demonstrates, in one small self-contained design:
//   - a packed enum type for the ALU opcode (readable in waveforms,
//     unlike a bare 3-bit code, and gives the compiler/simulator a
//     restricted value set to catch typos)
//   - a packed struct bundling the ALU result's status flags
//     (zero/carry/overflow) as a single typed object instead of three
//     loose wires
//   - an `interface` bundling the DUT<->testbench connection, with two
//     `modport`s (`dut` and `tb`) giving each side a *direction-checked*
//     view of the same signals -- the idiomatic reason to use an
//     interface at all
//
// TOOLING NOTES (found this session, 2026-08-24, all against the
// Icarus Verilog 10.3 build this repo's tools/setup_iverilog.sh
// installs -- see that script and the 2026-08-23 AUTOMATION_LOG.md
// entry for the two gaps found that day; this session found several
// more, all confirmed with minimal standalone repros before working
// around them here, so these are real toolchain limits, not bugs in
// this file's logic):
//
//   1. Interfaces cannot be used as module ports at all, in any syntax
//      form (`alu_if.dut vif`, `alu_if vif`, ANSI or non-ANSI style;
//      tried all four with `-g2012` and `-g2005-sv`) -- every form fails
//      with the same "Errors in port declarations" syntax error, even
//      for a two-line minimal interface with no modports. The interface
//      *declaration* below (with modports) compiles cleanly on its own;
//      it just cannot be used to type a module port on this build.
//   2. `always_comb` does not compile at all on this build, in any form
//      (single-statement or `begin/end` block), even completely
//      standalone with no ports, structs, or enums involved. Confirmed
//      with a 3-line minimal repro. `always_ff` likewise does not
//      compile (minimal repro: a 4-line register with async reset).
//      Plain Verilog-2001-style `always @*` and
//      `always @(posedge clk or negedge rst_n)` -- the style already
//      used throughout this repo's Phase 1 examples -- work fine and are
//      used below instead.
//   3. `unique case` / `priority case` do not compile; plain `case` (as
//      already used in Phase 1) works and is used below.
//   4. SystemVerilog assignment-pattern syntax (`'{default: 1'b0}`,
//      `'0` fill) does not compile for a packed-struct target; per-field
//      assignment (`flags.zero <= 1'b0;` etc.) works and is used below.
//
// Given (1)-(4), this Icarus 10.3 build's practical SystemVerilog support
// is closer to "Verilog-2001 plus typedef enum/struct and interface/
// always @* declarations" than to full IEEE 1800-2017 support -- useful
// to know heading into the rest of Phase 2 (classes, randomization,
// coverage are all *more* advanced SV than any of the above, so those
// examples should be spot-checked early too rather than assumed to
// compile, exactly as the 2026-08-23 log entry already anticipated).
// Because of (1), `alu_dut` below uses a plain (non-interface) port
// list -- see alu_if_tb.sv's header for how it is still connected
// through the `alu_if` interface instance via a named port map, and
// AUTOMATION_LOG.md (2026-08-24 entry) for the full summary.
//------------------------------------------------------------------------

`timescale 1ns/1ps

// 4-value packed enum -- default base type is `int` (2-state, 32-bit) but
// as a *port/interface field* it participates in the interface's 4-state
// `logic` signals, so X propagation still works if the DUT is unresolved
// or reset is not yet applied. Named values are far more readable than
// a bare 3'b010 in a waveform viewer or testbench trace.
typedef enum logic [2:0] {
    ALU_ADD = 3'b000,
    ALU_SUB = 3'b001,
    ALU_AND = 3'b010,
    ALU_OR  = 3'b011,
    ALU_XOR = 3'b100
} alu_op_e;

// Packed struct: bundles the three status flags into one typed field
// instead of three separate 1-bit ports. Packed (not just a SV struct)
// so it behaves like a single vector for waveform/VCD purposes and can
// be compared/assigned as a unit.
typedef struct packed {
    logic zero;
    logic carry;
    logic overflow;
} alu_flags_s;

// Interface bundling the full DUT<->TB connection for an 8-bit ALU.
// Using `logic` (not `wire`/`reg`) throughout, per SV convention, since
// `logic` can be driven by either continuous assignment or a procedural
// block and the simulator enforces single-driver rules regardless.
//
// See TOOLING NOTE (1) above: this interface's declaration compiles
// cleanly on Icarus 10.3 (verified); it is only *using it as a module
// port* (with or without a modport qualifier) that this build rejects.
// The modports below are the idiomatically-correct direction-checked
// views each side would use as its port type on a simulator with full
// interface-port support.
interface alu_if (input logic clk, input logic rst_n);
    logic  [7:0]   a, b;
    alu_op_e       op;
    logic          valid;
    logic  [7:0]   result;
    alu_flags_s    flags;
    logic          result_valid;

    // Intended DUT-side view (not usable as a port on this Icarus build
    // -- see TOOLING NOTE (1)): DUT reads stimulus fields as inputs,
    // drives result fields as outputs.
    modport dut (
        input  clk, rst_n, a, b, op, valid,
        output result, flags, result_valid
    );

    // Intended TB-side view (likewise not usable as a port here): mirror
    // image of the dut modport, from the same single point of
    // definition -- the value of interfaces over a raw port list is
    // that both sides' views are generated from one declaration instead
    // of two independently hand-maintained port lists that can silently
    // drift out of sync.
    modport tb (
        input  clk, rst_n, result, flags, result_valid,
        output a, b, op, valid
    );
endinterface

// Synchronous ALU DUT. Plain (non-interface) port list -- see TOOLING
// NOTE (1) above for why; this is the workaround for Icarus 10.3's lack
// of interface-port support, not the intended final form. Registers its
// inputs and result one cycle later (a deliberately simple pipeline
// stage, not purely combinational) so the example also exercises
// `result_valid` as a one-cycle-delayed valid signal -- a common real
// pattern the testbench must handle correctly.
module alu_dut (
    input  logic        clk,
    input  logic        rst_n,
    input  logic [7:0]  a,
    input  logic [7:0]  b,
    input  alu_op_e     op,
    input  logic        valid,
    output logic [7:0]  result,
    output alu_flags_s  flags,
    output logic        result_valid
);

    logic [7:0]  result_c;
    alu_flags_s  flags_c;
    logic [8:0]  add_ext, sub_ext; // 9-bit to catch carry/borrow

    // Combinational compute stage. Plain `always @*` -- see TOOLING
    // NOTE (2): `always_comb` does not compile on this Icarus build.
    always @* begin
        add_ext = {1'b0, a} + {1'b0, b};
        sub_ext = {1'b0, a} - {1'b0, b};

        // Plain `case` -- see TOOLING NOTE (3): `unique case` does not
        // compile on this Icarus build.
        case (op)
            ALU_ADD: result_c = add_ext[7:0];
            ALU_SUB: result_c = sub_ext[7:0];
            ALU_AND: result_c = a & b;
            ALU_OR:  result_c = a | b;
            ALU_XOR: result_c = a ^ b;
            default: result_c = 8'hxx; // unreachable given alu_op_e's
                                        // restricted value set, but kept
                                        // as an explicit safety default
        endcase

        flags_c.zero     = (result_c == 8'h00);
        flags_c.carry    = (op == ALU_ADD) ? add_ext[8] :
                            (op == ALU_SUB) ? sub_ext[8] : 1'b0;
        // Signed overflow: both operands same sign, result different sign
        // (only meaningful for ADD/SUB; 0 for logical ops)
        flags_c.overflow =
            (op == ALU_ADD) ? ((a[7] == b[7]) && (result_c[7] != a[7])) :
            (op == ALU_SUB) ? ((a[7] != b[7]) && (result_c[7] != a[7])) :
            1'b0;
    end

    // Registered (1-cycle-latency) output stage. Plain
    // `always @(posedge clk or negedge rst_n)` -- see TOOLING NOTE (2):
    // `always_ff` does not compile on this Icarus build. Per-field
    // struct reset assignment -- see TOOLING NOTE (4): the
    // `'{default: 1'b0}` assignment-pattern syntax does not compile on
    // this Icarus build.
    always @(posedge clk or negedge rst_n) begin
        if (!rst_n) begin
            result          <= 8'h00;
            flags.zero      <= 1'b0;
            flags.carry     <= 1'b0;
            flags.overflow  <= 1'b0;
            result_valid    <= 1'b0;
        end else begin
            result       <= result_c;
            flags        <= flags_c;
            result_valid <= valid;
        end
    end

endmodule

examples/phase2/alu_sva_checker.sv
//------------------------------------------------------------------------
// alu_sva_checker.sv
//
// Phase 2 example: "Basic SVA (assert property, immediate vs.
// concurrent)" -- the progress.md item after functional coverage
// (2026-08-26, second session). Reuses alu_dut from alu_if_and_dut.sv
// unmodified, exactly as every other Phase 2 ALU example does.
//
// TOOLING FINDING (this session, 2026-08-28, confirmed with minimal
// standalone repros in /tmp/repro/ against the genuine pinned Icarus
// Verilog 10.3 toolchain (tools/setup_iverilog.sh) before being treated
// as established -- see notes/2026-08-28-sva-immediate-vs-concurrent-
// assertions.md for full repro listings, captured compiler output, and
// a secondary data point from Icarus Verilog 12.0):
//
//   Neither assertion flavor is implemented on this build:
//     - Immediate assertions (`assert (expr) else action;`, and the
//       `assert #0 (...)` variant) fail to compile: "sorry: Simple
//       immediate assertion statements not implemented." This
//       re-confirms the 2026-08-23 finding rather than assuming it still
//       holds.
//     - Concurrent assertions (`assert property (...)`, and even a
//       standalone `property ... endproperty` block on its own) also
//       fail, with an explicit "sorry: concurrent_assertion_item not
//       supported" message.
//   This is a clean, total gap (like 2026-08-26's randomize()/covergroup
//   findings), not a partial-support nuance -- so, exactly as those
//   examples did, this file demonstrates the underlying CONCEPT (a
//   dedicated, DUT-adjacent assertion-style checker, separate from
//   stimulus generation -- see notes file Section 1's last bullet for
//   why that separation matters, independent of concrete syntax) using
//   the `if (!cond) $error(...)` idiom this repo has used as the
//   immediate-assertion substitute since 2026-08-23, rather than native
//   `assert`/`assert property` syntax.
//
// TWO FURTHER TOOLING GAPS found while building this file (both new
// today, both confirmed by the compiler's own message rather than
// assumed): (1) a `function automatic void` with `output` arguments is
// rejected ("Function arguments must be input ports" -- Icarus 10.3
// functions apparently must be single-return-value only); worked around
// by declaring alu_ref_model as a `task automatic` instead, which does
// accept output arguments. (2) `enum_value.name()` used as a `$error`
// format argument is rejected ("Enumeration method name() is not
// currently supported in this context (self-determined)"); worked
// around by printing the raw enum-underlying value with %0d instead.
//
// WHAT MAKES THIS DIFFERENT FROM PRIOR ALU EXAMPLES: every earlier
// Phase 2 file (alu_if_tb.sv, alu_oop_tb_components.sv,
// alu_manual_constrained_random.sv, alu_manual_functional_coverage.sv)
// embeds its correctness checks inline within a stimulus-driving
// testbench. This file instead structures checking as a SEPARATE
// concern (the apply_and_check task below focuses purely on comparing
// DUT outputs to an independent reference model; a real assertion-based
// verification environment would express this as a `bind`-attached
// checker module or a set of `assert property` statements living
// alongside the DUT, decoupled entirely from whatever testbench drives
// stimulus) -- the architectural point Phase 3 (layered testbench
// architecture) will formalize further.
//------------------------------------------------------------------------

`timescale 1ns/1ps

module alu_sva_checker_tb;

    logic        clk = 0;
    logic        rst_n;
    logic [7:0]  a, b;
    alu_op_e     op;
    logic        valid;
    logic [7:0]  result;
    alu_flags_s  flags;
    logic        result_valid;

    always #5 clk = ~clk;

    alu_dut dut (
        .clk(clk), .rst_n(rst_n),
        .a(a), .b(b), .op(op), .valid(valid),
        .result(result), .flags(flags), .result_valid(result_valid)
    );

    int checks_run    = 0;
    int checks_passed = 0;

    // -------------------------------------------------------------
    // Independent reference model / "checker". See file header for
    // why the formulations below deliberately do NOT reuse alu_dut's
    // own internal expressions (a shared bug in "the obvious way to
    // compute this" would otherwise silently cancel out between DUT
    // and checker, exactly the failure mode an independent reference
    // model exists to avoid -- the same principle already used for
    // sync_fifo_directed_tb.v's independent reference queue,
    // 2026-08-23).
    // -------------------------------------------------------------
    task automatic alu_ref_model(
        input  logic [7:0] a_in, b_in,
        input  alu_op_e    op_in,
        output logic [7:0] exp_result,
        output logic        exp_zero,
        output logic        exp_carry,
        output logic        exp_overflow
    );
        logic signed [15:0] true_wide; // full-precision signed result,
                                        // no truncation -- used to detect
                                        // overflow by comparing against
                                        // the (possibly-truncated)
                                        // 8-bit signed result below
        begin
            case (op_in)
                ALU_ADD: begin
                    exp_result = a_in + b_in; // natural 8-bit wraparound
                    // Unsigned carry via comparison against the
                    // complement, not via a widened 9-bit add (that is
                    // the DUT's approach -- see add_ext[8] in
                    // alu_if_and_dut.sv).
                    exp_carry  = (a_in > (8'hFF - b_in));
                    true_wide  = $signed({{8{a_in[7]}}, a_in}) +
                                 $signed({{8{b_in[7]}}, b_in});
                    exp_overflow = (true_wide !=
                                    $signed({{8{exp_result[7]}}, exp_result}));
                end
                ALU_SUB: begin
                    exp_result = a_in - b_in; // natural 8-bit wraparound
                    // Unsigned borrow via direct magnitude comparison,
                    // not via a widened 9-bit subtract (the DUT's
                    // sub_ext[8] approach).
                    exp_carry  = (a_in < b_in);
                    true_wide  = $signed({{8{a_in[7]}}, a_in}) -
                                 $signed({{8{b_in[7]}}, b_in});
                    exp_overflow = (true_wide !=
                                    $signed({{8{exp_result[7]}}, exp_result}));
                end
                ALU_AND: begin
                    exp_result = a_in & b_in;
                    exp_carry = 1'b0; exp_overflow = 1'b0;
                end
                ALU_OR: begin
                    exp_result = a_in | b_in;
                    exp_carry = 1'b0; exp_overflow = 1'b0;
                end
                ALU_XOR: begin
                    exp_result = a_in ^ b_in;
                    exp_carry = 1'b0; exp_overflow = 1'b0;
                end
                default: begin
                    exp_result = 8'hxx; exp_carry = 1'bx; exp_overflow = 1'bx;
                end
            endcase
            exp_zero = (exp_result == 8'h00);
        end
    endtask

    // Remembers the operands/op used for the transaction currently in
    // flight, so the checker (running one cycle later, once
    // result_valid rises) checks against the SAME inputs that produced
    // the DUT's registered output -- not whatever a, b, op happen to
    // hold combinationally at check time.
    logic [7:0] a_q, b_q;
    alu_op_e    op_q;

    // Applies one ALU operation, waits for the registered result, then
    // checks it -- structured as a standalone checker step, deliberately
    // separate from any notion of "generate the next random stimulus"
    // (see file header). `corrupt` deliberately feeds the checker a
    // wrong expected value (the DUT and its actual inputs are untouched)
    // to prove the checks really do fire, not just always pass -- mirrors
    // sync_fifo_directed_tb.v's deliberate illegal-push/illegal-pop
    // checks (2026-08-23).
    task automatic apply_and_check(
        input logic [7:0] a_val, b_val,
        input alu_op_e    op_val,
        input string       label,
        input bit          corrupt = 1'b0
    );
        logic [7:0] exp_result, corrupted_result;
        logic        exp_zero, exp_carry, exp_overflow;
        begin
            @(posedge clk);
            a <= a_val; b <= b_val; op <= op_val; valid <= 1'b1;
            a_q <= a_val; b_q <= b_val; op_q <= op_val;

            @(posedge clk);
            valid <= 1'b0;

            // Give the registered outputs one delta cycle to settle
            // before sampling them (they were clocked on the edge we
            // just crossed).
            #1;

            checks_run++;
            if (!(result_valid === 1'b1))
                $error("[%0t] %s: expected result_valid=1, got %0b",
                        $time, label, result_valid);

            alu_ref_model(a_q, b_q, op_q, exp_result, exp_zero, exp_carry, exp_overflow);

            if (corrupt) begin
                // Deliberately wrong expected value -- injected into the
                // CHECK, not into the DUT -- so this check is guaranteed
                // to fail. Flips every bit of the correct result so it
                // can never accidentally match by chance.
                corrupted_result = ~exp_result;
                if (!(result === corrupted_result))
                    $error("[%0t] %s: EXPECTED-FAIL (deliberate): result=%0h did not match deliberately-wrong expected=%0h (real expected was %0h) -- this failure is correct and proves the checker works",
                            $time, label, result, corrupted_result, exp_result);
            end else begin
                if (!(result === exp_result))
                    $error("[%0t] %s: result mismatch: dut=%0h expected=%0h (a=%0h b=%0h op_code=%0d)",
                            $time, label, result, exp_result, a_q, b_q, op_q);
                if (!(flags.zero === exp_zero))
                    $error("[%0t] %s: zero flag mismatch: dut=%0b expected=%0b",
                            $time, label, flags.zero, exp_zero);
                if (!(flags.carry === exp_carry))
                    $error("[%0t] %s: carry flag mismatch: dut=%0b expected=%0b",
                            $time, label, flags.carry, exp_carry);
                if (!(flags.overflow === exp_overflow))
                    $error("[%0t] %s: overflow flag mismatch: dut=%0b expected=%0b",
                            $time, label, flags.overflow, exp_overflow);
                checks_passed++;
            end
        end
    endtask

    initial begin
        $dumpfile("alu_sva_checker_wave.vcd");
        $dumpvars(0, alu_sva_checker_tb);

        rst_n = 0; a = 0; b = 0; op = ALU_ADD; valid = 0;
        repeat (2) @(posedge clk);
        rst_n = 1;
        @(posedge clk);

        // --- ADD: normal, carry, zero-result, signed overflow ---
        apply_and_check(8'h05, 8'h03, ALU_ADD, "ADD normal (5+3=8)");
        apply_and_check(8'hFF, 8'h01, ALU_ADD, "ADD wrap+carry (0xFF+1=0x00, carry)");
        apply_and_check(8'h00, 8'h00, ALU_ADD, "ADD zero result");
        apply_and_check(8'h7F, 8'h01, ALU_ADD, "ADD signed overflow (MAX_POS+1)");
        apply_and_check(8'h80, 8'h80, ALU_ADD, "ADD signed overflow (MIN_NEG+MIN_NEG)");

        // --- SUB: normal, borrow, zero result, signed overflow ---
        apply_and_check(8'h08, 8'h03, ALU_SUB, "SUB normal (8-3=5)");
        apply_and_check(8'h00, 8'h01, ALU_SUB, "SUB borrow (0-1=0xFF, borrow)");
        apply_and_check(8'h42, 8'h42, ALU_SUB, "SUB zero result");
        apply_and_check(8'h80, 8'h01, ALU_SUB, "SUB signed overflow (MIN_NEG-1)");
        apply_and_check(8'h7F, 8'hFF, ALU_SUB, "SUB signed overflow (MAX_POS-(-1))");

        // --- Logical ops: no carry/overflow possible ---
        apply_and_check(8'hF0, 8'h0F, ALU_AND, "AND disjoint bits -> 0");
        apply_and_check(8'hF0, 8'h0F, ALU_OR,  "OR disjoint bits -> 0xFF");
        apply_and_check(8'hAA, 8'hFF, ALU_XOR, "XOR with all-ones -> complement");
        apply_and_check(8'h00, 8'h00, ALU_AND, "AND zero result");

        // --- Deliberate expected-fail: proves the checker actually
        //     catches a wrong result, not just that it always passes.
        apply_and_check(8'h10, 8'h20, ALU_ADD, "deliberate corrupted-expectation check", 1'b1);

        $display("--------------------------------------------------------");
        $display("Total checks = %0d, passed = %0d, deliberate-fail cases = 1",
                  checks_run, checks_passed);
        if (checks_passed == checks_run - 1)
            $display("PASS: all real checks matched the independent reference model; the one deliberate corrupted-expectation case correctly failed above.");
        else
            $display("FAIL: unexpected number of passing checks -- investigate.");
        $finish;
    end

endmodule

examples/phase2/alu_sva_checker_wave.vcd
$date
	Fri Aug 28 17:48:36 2026
$end
$version
	Icarus Verilog
$end
$timescale
	1ps
$end
$scope module alu_sva_checker_tb $end
$var wire 1 ! result_valid $end
$var wire 8 " result [7:0] $end
$var wire 3 # flags [2:0] $end
$var reg 8 $ a [7:0] $end
$var reg 8 % a_q [7:0] $end
$var reg 8 & b [7:0] $end
$var reg 8 ' b_q [7:0] $end
$var reg 1 ( clk $end
$var reg 3 ) op [2:0] $end
$var reg 3 * op_q [2:0] $end
$var reg 1 + rst_n $end
$var reg 1 , valid $end
$var integer 32 - checks_passed [31:0] $end
$var integer 32 . checks_run [31:0] $end
$scope module dut $end
$var wire 8 / a [7:0] $end
$var wire 8 0 b [7:0] $end
$var wire 1 ( clk $end
$var wire 3 1 op [2:0] $end
$var wire 1 + rst_n $end
$var wire 1 , valid $end
$var reg 9 2 add_ext [8:0] $end
$var reg 3 3 flags [2:0] $end
$var reg 3 4 flags_c [2:0] $end
$var reg 8 5 result [7:0] $end
$var reg 8 6 result_c [7:0] $end
$var reg 1 ! result_valid $end
$var reg 9 7 sub_ext [8:0] $end
$upscope $end
$scope task alu_ref_model $end
$upscope $end
$scope task apply_and_check $end
$upscope $end
$upscope $end
$enddefinitions $end
$comment Show the parameter values. $end
$dumpall
$end
#0
$dumpvars
b0 7
b0 6
b0 5
b100 4
b0 3
b0 2
b0 1
b0 0
b0 /
b0 .
b0 -
0,
0+
bx *
b0 )
0(
bx '
b0 &
bx %
b0 $
b0 #
b0 "
0!
$end
#5000
1(
#10000
0(
#15000
b100 #
b100 3
1+
1(
#20000
0(
#25000
1(
#30000
0(
#35000
b0 4
b1000 6
b10 7
b1000 2
b0 *
b11 '
b101 %
1,
b11 &
b11 0
b101 $
b101 /
1(
#40000
0(
#45000
1!
b0 #
b0 3
b1000 "
b1000 5
0,
1(
#46000
b1 -
b1 .
#50000
0(
#55000
b110 4
b0 6
b11111110 7
b100000000 2
0!
b1 '
b11111111 %
1,
b1 &
b1 0
b11111111 $
b11111111 /
1(
#60000
0(
#65000
1!
b110 #
b110 3
b0 "
b0 5
0,
1(
#66000
b10 -
b10 .
#70000
0(
#75000
b100 4
b0 7
b0 2
0!
b0 '
b0 %
1,
b0 &
b0 0
b0 $
b0 /
1(
#80000
0(
#85000
1!
b100 #
b100 3
0,
1(
#86000
b11 -
b11 .
#90000
0(
#95000
b1 4
b10000000 6
b1111110 7
b10000000 2
0!
b1 '
b1111111 %
1,
b1 &
b1 0
b1111111 $
b1111111 /
1(
#100000
0(
#105000
1!
b1 #
b1 3
b10000000 "
b10000000 5
0,
1(
#106000
b100 -
b100 .
#110000
0(
#115000
b111 4
b0 6
b0 7
b100000000 2
0!
b10000000 '
b10000000 %
1,
b10000000 &
b10000000 0
b10000000 $
b10000000 /
1(
#120000
0(
#125000
1!
b111 #
b111 3
b0 "
b0 5
0,
1(
#126000
b101 -
b101 .
#130000
0(
#135000
b0 4
b101 6
b101 7
b1011 2
0!
b1 *
b11 '
b1000 %
1,
b1 )
b1 1
b11 &
b11 0
b1000 $
b1000 /
1(
#140000
0(
#145000
1!
b0 #
b0 3
b101 "
b101 5
0,
1(
#146000
b110 -
b110 .
#150000
0(
#155000
b10 4
b11111111 6
b111111111 7
b1 2
0!
b1 '
b0 %
1,
b1 &
b1 0
b0 $
b0 /
1(
#160000
0(
#165000
1!
b10 #
b10 3
b11111111 "
b11111111 5
0,
1(
#166000
b111 -
b111 .
#170000
0(
#175000
b100 4
b0 6
b0 7
b10000100 2
0!
b1000010 '
b1000010 %
1,
b1000010 &
b1000010 0
b1000010 $
b1000010 /
1(
#180000
0(
#185000
1!
b100 #
b100 3
b0 "
b0 5
0,
1(
#186000
b1000 -
b1000 .
#190000
0(
#195000
b1 4
b1111111 6
b1111111 7
b10000001 2
0!
b1 '
b10000000 %
1,
b1 &
b1 0
b10000000 $
b10000000 /
1(
#200000
0(
#205000
1!
b1 #
b1 3
b1111111 "
b1111111 5
0,
1(
#206000
b1001 -
b1001 .
#210000
0(
#215000
b11 4
b10000000 6
b110000000 7
b101111110 2
0!
b11111111 '
b1111111 %
1,
b11111111 &
b11111111 0
b1111111 $
b1111111 /
1(
#220000
0(
#225000
1!
b11 #
b11 3
b10000000 "
b10000000 5
0,
1(
#226000
b1010 -
b1010 .
#230000
0(
#235000
b100 4
b0 6
b11100001 7
b11111111 2
0!
b10 *
b1111 '
b11110000 %
1,
b10 )
b10 1
b1111 &
b1111 0
b11110000 $
b11110000 /
1(
#240000
0(
#245000
1!
b100 #
b100 3
b0 "
b0 5
0,
1(
#246000
b1011 -
b1011 .
#250000
0(
#255000
b0 4
b11111111 6
0!
b11 *
1,
b11 )
b11 1
1(
#260000
0(
#265000
1!
b0 #
b0 3
b11111111 "
b11111111 5
0,
1(
#266000
b1100 -
b1100 .
#270000
0(
#275000
b1010101 6
b110101011 7
b110101001 2
0!
b100 *
b11111111 '
b10101010 %
1,
b100 )
b100 1
b11111111 &
b11111111 0
b10101010 $
b10101010 /
1(
#280000
0(
#285000
1!
b1010101 "
b1010101 5
0,
1(
#286000
b1101 -
b1101 .
#290000
0(
#295000
b100 4
b0 6
b0 7
b0 2
0!
b10 *
b0 '
b0 %
1,
b10 )
b10 1
b0 &
b0 0
b0 $
b0 /
1(
#300000
0(
#305000
1!
b100 #
b100 3
b0 "
b0 5
0,
1(
#306000
b1110 -
b1110 .
#310000
0(
#315000
b0 4
b110000 6
b111110000 7
b110000 2
0!
b0 *
b100000 '
b10000 %
1,
b0 )
b0 1
b100000 &
b100000 0
b10000 $
b10000 /
1(
#320000
0(
#325000
1!
b0 #
b0 3
b110000 "
b110000 5
0,
1(
#326000
b1111 .
